arp_jarvis_runtime-0.1.0.dist-info/licenses/LICENSE
jarvis_runtime/__init__.py
jarvis_runtime/__main__.py
jarvis_runtime/cli.py
jarvis_runtime/json_schema.py
jarvis_runtime/orchestrator.py
jarvis_runtime/server.py
jarvis_runtime/tool_registry_client.py
jarvis_runtime/trace.py
jarvis_runtime/util.py
jarvis_runtime/llm/__init__.py
jarvis_runtime/llm/client.py
jarvis_runtime/llm/openai_responses_client.py
jarvis_runtime/roles/__init__.py
jarvis_runtime/roles/chat.py
jarvis_runtime/roles/planner.py
jarvis_runtime/roles/tool_args.py
jarvis_runtime/roles/tool_executor.py
arp_jarvis_runtime-0.1.0.dist-info/METADATA
arp_jarvis_runtime-0.1.0.dist-info/WHEEL
arp_jarvis_runtime-0.1.0.dist-info/entry_points.txt
arp_jarvis_runtime-0.1.0.dist-info/top_level.txt
arp_jarvis_runtime-0.1.0.dist-info/RECORD
